isaac_neural/__init__.py
isaac_neural/telemetry.py
isaac_neural/agentic/__init__.py
isaac_neural/agentic/controller_executor.py
isaac_neural/agentic/interfaces.py
isaac_neural/agentic/adapters/__init__.py
isaac_neural/agentic/adapters/reasoning_adapter.py
isaac_neural/agentic/adapters/reflexion_adapter.py
isaac_neural/agentic/adapters/verifier_adapter.py
isaac_neural/controller/__init__.py
isaac_neural/controller/executor.py
isaac_neural/controller/merge_utils.py
isaac_neural/controller/model_client.py
isaac_neural/controller/routing.py
isaac_neural/controller/tool_runner.py
isaac_neural/controller/verifier_client.py
isaac_neural/critique/dto.py
isaac_neural/graph/types.py
isaac_neural/models/__init__.py
isaac_neural/models/isaac_patch_v1.py
isaac_neural/models/schemas.py
isaac_neural/prompting/__init__.py
isaac_neural/prompting/high_powered_agent.py
isaac_neural/reflexion/types.py
isaac_neural/resources/config/ab_rollout.yaml
isaac_neural/resources/config/agentic.yaml
isaac_neural/resources/config/router.yaml
isaac_neural/resources/config/verifier.yaml
isaac_neural/resources/config/schemas/isaac_patch_v1.json
isaac_neural/resources/prompts/controller.system.txt
isaac_neural/resources/prompts/planner.system.txt
isaac_neural/resources/prompts/reflexion.system.txt
isaac_neural/tests/test_controller_smoke.py
isaac_neural/tests/test_prompt_agent.py
isaac_neural/tests/test_routing.py
isaac_neural_core-0.1.1.dist-info/METADATA
isaac_neural_core-0.1.1.dist-info/WHEEL
isaac_neural_core-0.1.1.dist-info/top_level.txt
isaac_neural_core-0.1.1.dist-info/RECORD
