Metadata-Version: 2.4
Name: isaac-neural-core
Version: 0.1.1
Summary: ISAAC Neural Orchestrator core library (planner/routing/generation/verification/reflexion)
Author: ISAAC
License: MIT
Project-URL: Homepage, https://github.com/pedroMantAmp/isaac-neural-core
Project-URL: Repository, https://github.com/pedroMantAmp/isaac-neural-core
Requires-Python: >=3.11
Requires-Dist: pydantic<3,>=2.5
Requires-Dist: httpx<1,>=0.24
Requires-Dist: pyyaml<7,>=6
